utf8_tokenizer/__init__.py
utf8_tokenizer/byt5_comparison.py
utf8_tokenizer/byte_embeddings.py
utf8_tokenizer/char_causal_lm.py
utf8_tokenizer/char_embeddings.py
utf8_tokenizer/chat_template.jinja
utf8_tokenizer/control.py
utf8_tokenizer/logits_processor.py
utf8_tokenizer/tokenizer.py
utf8_tokenizer/utils.py
utf8_tokenizer-0.7.1.dist-info/licenses/LICENSE
utf8_tokenizer-0.7.1.dist-info/METADATA
utf8_tokenizer-0.7.1.dist-info/WHEEL
utf8_tokenizer-0.7.1.dist-info/top_level.txt
utf8_tokenizer-0.7.1.dist-info/RECORD
