Metadata-Version: 2.4
Name: utf8-tokenizer
Version: 0.7.1
Summary: True UTF-8 tokenizer for byte level models
Author-email: Amit Moryossef <amit@sign.mt>
Requires-Python: >=3.10
License-File: LICENSE
Requires-Dist: transformers[torch]
Requires-Dist: torch
Provides-Extra: dev
Requires-Dist: ruff; extra == "dev"
Requires-Dist: pytest; extra == "dev"
Requires-Dist: pytest-xdist; extra == "dev"
Provides-Extra: fast
Requires-Dist: numba; extra == "fast"
Provides-Extra: train
Requires-Dist: datasets; extra == "train"
Requires-Dist: evaluate; extra == "train"
Requires-Dist: scikit-learn; extra == "train"
Requires-Dist: wandb; extra == "train"
Dynamic: license-file
